launch_cert_tool/__init__.py
launch_cert_tool/cli.py
launch_cert_tool/parser.py
launch_cert_tool/validate.py
launch_cert_tool-1.1.0.dist-info/METADATA
launch_cert_tool-1.1.0.dist-info/WHEEL
launch_cert_tool-1.1.0.dist-info/entry_points.txt
launch_cert_tool-1.1.0.dist-info/top_level.txt
launch_cert_tool-1.1.0.dist-info/RECORD
