Metadata-Version: 2.4
Name: launch-cert-tool
Version: 1.1.0
Summary: CLI tool to assist with certificate management
License: Apache 2.0
Project-URL: Homepage, https://github.com/launchbynttdata/launch-cert-tool
Project-URL: Issues, https://github.com/launchbynttdata/launch-cert-tool/issues
Classifier: Programming Language :: Python :: 3
Classifier: License :: OSI Approved :: MIT License
Classifier: Operating System :: OS Independent
Classifier: Development Status :: 5 - Production/Stable
Classifier: Environment :: Console
Classifier: Intended Audience :: System Administrators
Classifier: Topic :: Security
Classifier: Topic :: Software Development :: Testing
Classifier: Topic :: Utilities
Requires-Python: >=3.13
Requires-Dist: arn>=0.1.5
Requires-Dist: boto3>=1.36.7
Requires-Dist: certifi>=2024.12.14
Requires-Dist: cryptography>=43.0.3
Requires-Dist: pki-tools>=1.0.6
Requires-Dist: requests>=2.32.3
Requires-Dist: typer>=0.15.1
